algorithmx/__init__.py
algorithmx/_version.py
algorithmx/main.py
algorithmx/api/Canvas.py
algorithmx/api/EdgeSelection.py
algorithmx/api/ElementSelection.py
algorithmx/api/LabelSelection.py
algorithmx/api/NodeSelection.py
algorithmx/api/QueueSelection.py
algorithmx/api/__init__.py
algorithmx/api/types.py
algorithmx/api/utils.py
algorithmx/jupyter/JupyterCanvas.py
algorithmx/jupyter/__init__.py
algorithmx/jupyter/extension.py
algorithmx/labextension/algorithmx-jupyter-3.0.1.tgz
algorithmx/nbextension/extension.js
algorithmx/nbextension/extension.js.LICENSE.txt
algorithmx/nbextension/extension.js.map
algorithmx/networkx/__init__.py
algorithmx/networkx/utils.py
algorithmx/server/CanvasServer.py
algorithmx/server/FileServer.py
algorithmx/server/WebsocketServer.py
algorithmx/server/__init__.py
algorithmx/server/algorithmx.html
algorithmx/server/websocket.py
algorithmx/server/dist/index.js
algorithmx/server/dist/index.js.LICENSE.txt
algorithmx/server/dist/index.js.map
algorithmx-2.0.3.data/data/etc/jupyter/nbconfig/notebook.d/algorithmx-jupyter.json
algorithmx-2.0.3.data/data/share/jupyter/lab/extensions/algorithmx-jupyter-3.0.1.tgz
algorithmx-2.0.3.data/data/share/jupyter/nbextensions/algorithmx-jupyter/extension.js
algorithmx-2.0.3.data/data/share/jupyter/nbextensions/algorithmx-jupyter/extension.js.LICENSE.txt
algorithmx-2.0.3.data/data/share/jupyter/nbextensions/algorithmx-jupyter/extension.js.map
tests/__init__.py
tests/test_api.py
algorithmx-2.0.3.dist-info/LICENSE.txt
algorithmx-2.0.3.dist-info/METADATA
algorithmx-2.0.3.dist-info/WHEEL
algorithmx-2.0.3.dist-info/top_level.txt
algorithmx-2.0.3.dist-info/RECORD
