Metadata-Version: 2.1
Name: algorithmx
Version: 2.0.3
Summary: A library for network visualization and algorithm simulation.
Home-page: https://github.com/algrx/algorithmx-python
Author: Alex Socha
Author-email: algorithmx.lib@gmail.com
License: MIT
Keywords: Jupyter,JupyterLab,IPython
Platform: Linux
Platform: MacOS
Platform: Windows
Classifier: Intended Audience :: Developers
Classifier: Intended Audience :: Science/Research
Classifier: License :: OSI Approved :: MIT License
Classifier: Programming Language :: Python
Classifier: Programming Language :: Python :: 3
Classifier: Programming Language :: Python :: 3.7
Classifier: Framework :: Jupyter
Provides-Extra: jupyter
Requires-Dist: ipywidgets (>=7.0.0) ; extra == 'jupyter'
Requires-Dist: jupyterlab (>=2.0.0) ; extra == 'jupyter'
Provides-Extra: networkx
Requires-Dist: networkx (>=2.5) ; extra == 'networkx'
